flyvar/__init__.py
flyvar-1.0.6.dist-info/LICENSE
flyvar-1.0.6.dist-info/METADATA
flyvar-1.0.6.dist-info/WHEEL
flyvar-1.0.6.dist-info/top_level.txt
flyvar-1.0.6.dist-info/RECORD
