Metadata-Version: 2.1
Name: flyvar
Version: 1.0.6
Summary: A database that is convenient for version iteration
Home-page: https://github.com/snbck/flyvar
Author: snbckcode
Author-email: snbckcode@gmail.com
License: Mozilla
Keywords: A database that is convenient for version iteration
Platform: UNKNOWN
Requires-Python: >=3.6
Requires-Dist: huepy
